setup.py
idauth/__init__.py
idauth/auth_request.py
idauth/auth_response.py
idauth/exceptions.py
idauth/identifier.py
idauth/keys.py
idauth/permissions.py
idauth/tokenizer.py
idauth/utils.py
idauth.egg-info/PKG-INFO
idauth.egg-info/SOURCES.txt
idauth.egg-info/dependency_links.txt
idauth.egg-info/not-zip-safe
idauth.egg-info/requires.txt
idauth.egg-info/top_level.txt