Metadata-Version: 1.1
Name: idauth
Version: 0.0.0
Summary: Blockchain ID Auth Library
Home-page: https://github.com/blockstack/blockchain-id-auth
Author: Blockstack Developers
Author-email: hello@onename.com
License: MIT
Keywords: bitcoin btc litecoin namecoin dogecoin cryptocurrency
Platform: UNKNOWN
Classifier: Intended Audience :: Developers
Classifier: License :: OSI Approved :: MIT License
Classifier: Operating System :: OS Independent
Classifier: Programming Language :: Python
Classifier: Topic :: Internet
Classifier: Topic :: Security :: Cryptography
Classifier: Topic :: Software Development :: Libraries :: Python Modules
